brian2_loihi/__init__.py
brian2_loihi/constants.py
brian2_loihi/loihi_network.py
brian2_loihi/loihi_neuron_group.py
brian2_loihi/loihi_spike_generator_group.py
brian2_loihi/loihi_spike_monitor.py
brian2_loihi/loihi_state_monitor.py
brian2_loihi/loihi_synapses.py
brian2_loihi/parameter_checks.py
brian2_loihi-0.5.2.dist-info/METADATA
brian2_loihi-0.5.2.dist-info/WHEEL
brian2_loihi-0.5.2.dist-info/top_level.txt
brian2_loihi-0.5.2.dist-info/RECORD
