Metadata-Version: 2.1
Name: brian2-loihi
Version: 0.5.2
Summary: A Loihi emulator based on Brian2
Home-page: https://github.com/sagacitysite/brian2_loihi
Author: Carlo Michaelis, Andrew Lehr & Winfried Oed
Author-email: carlo.michaelis@gmail.com
License: UNKNOWN
Platform: UNKNOWN
Classifier: Programming Language :: Python :: 3
Classifier: License :: OSI Approved :: MIT License
Classifier: Operating System :: OS Independent
Requires-Python: >3.6
Requires-Dist: brian2 (>=2.4.2)
Requires-Dist: numpy
